streamlit_oauth/__init__.py
streamlit_oauth/frontend/dist/index.html
streamlit_oauth/frontend/dist/vite.svg
streamlit_oauth/frontend/dist/assets/index-D4u-BQUG.css
streamlit_oauth/frontend/dist/assets/index-DCTU_4ac.js
streamlit_oauth/frontend/dist/assets/index.1c9175a0.js
streamlit_oauth/frontend/dist/assets/index.ed68cfaf.css
streamlit_oauth-0.1.14.dist-info/LICENSE
streamlit_oauth-0.1.14.dist-info/METADATA
streamlit_oauth-0.1.14.dist-info/WHEEL
streamlit_oauth-0.1.14.dist-info/top_level.txt
streamlit_oauth-0.1.14.dist-info/RECORD
