Metadata-Version: 2.1
Name: streamlit-oauth
Version: 0.1.14
Summary: Simple OAuth2 authorization code flow for Streamlit
Home-page: https://github.com/dnplus/streamlit-oauth
Author: Dylan Lu
Author-email: dnplus@gmail.com
Requires-Python: >=3.9
License-File: LICENSE
Requires-Dist: streamlit>=1.28.1
Requires-Dist: httpx-oauth==0.15.1
Requires-Dist: python-dotenv==1.0.1
